{"summary":{"Alappuzha":{"hospital_obs":1108,"home_obs":5660,"total_obs":6768,"hospital_today":30,"confirmed":2779,"recovered":1592,"deceased":8,"active":1176},"Ernakulam":{"hospital_obs":1179,"home_obs":11549,"total_obs":12728,"hospital_today":114,"confirmed":2955,"recovered":1733,"deceased":19,"active":1195},"Idukki":{"hospital_obs":238,"home_obs":3499,"total_obs":3737,"hospital_today":21,"confirmed":1086,"recovered":838,"deceased":2,"active":245},"Kannur":{"hospital_obs":415,"home_obs":8316,"total_obs":8731,"hospital_today":76,"confirmed":1780,"recovered":1357,"deceased":10,"active":412},"Kasaragod":{"hospital_obs":1027,"home_obs":3817,"total_obs":4844,"hospital_today":73,"confirmed":2936,"recovered":1836,"deceased":12,"active":1086},"Kollam":{"hospital_obs":673,"home_obs":6933,"total_obs":7606,"hospital_today":58,"confirmed":2246,"recovered":1665,"deceased":9,"active":571},"Kottayam":{"hospital_obs":445,"home_obs":9660,"total_obs":10105,"hospital_today":45,"confirmed":1718,"recovered":1293,"deceased":1,"active":424},"Kozhikode":{"hospital_obs":1053,"home_obs":13156,"total_obs":14209,"hospital_today":187,"confirmed":2567,"recovered":1398,"deceased":14,"active":1151},"Malappuram":{"hospital_obs":1340,"home_obs":31618,"total_obs":32958,"hospital_today":281,"confirmed":3762,"recovered":2137,"deceased":10,"active":1612},"Palakkad":{"hospital_obs":639,"home_obs":10939,"total_obs":11578,"hospital_today":132,"confirmed":2610,"recovered":1824,"deceased":2,"active":782},"Pathanamthitta":{"hospital_obs":214,"home_obs":4887,"total_obs":5101,"hospital_today":10,"confirmed":1821,"recovered":1558,"deceased":1,"active":260},"Thiruvananthapuram":{"hospital_obs":2955,"home_obs":15879,"total_obs":18834,"hospital_today":360,"confirmed":7632,"recovered":4602,"deceased":22,"active":2990},"Thrissur":{"hospital_obs":484,"home_obs":9224,"total_obs":9708,"hospital_today":28,"confirmed":2101,"recovered":1573,"deceased":8,"active":519},"Wayanad":{"hospital_obs":351,"home_obs":2449,"total_obs":2800,"hospital_today":41,"confirmed":939,"recovered":636,"deceased":2,"active":301}},"delta":{"Alappuzha":{"hospital_obs":4,"home_obs":-426,"total_obs":-422,"hospital_today":-80,"confirmed":146,"recovered":70,"deceased":0,"active":76},"Ernakulam":{"hospital_obs":-58,"home_obs":450,"total_obs":392,"hospital_today":53,"confirmed":133,"recovered":70,"deceased":1,"active":62},"Idukki":{"hospital_obs":-48,"home_obs":-63,"total_obs":-111,"hospital_today":-2,"confirmed":4,"recovered":68,"deceased":0,"active":-64},"Kannur":{"hospital_obs":34,"home_obs":-222,"total_obs":-188,"hospital_today":31,"confirmed":30,"recovered":27,"deceased":1,"active":2},"Kasaragod":{"hospital_obs":61,"home_obs":82,"total_obs":143,"hospital_today":33,"confirmed":147,"recovered":266,"deceased":0,"active":-119},"Kollam":{"hospital_obs":54,"home_obs":-158,"total_obs":-104,"hospital_today":-6,"confirmed":25,"recovered":32,"deceased":0,"active":-7},"Kottayam":{"hospital_obs":-11,"home_obs":408,"total_obs":397,"hospital_today":-98,"confirmed":24,"recovered":47,"deceased":0,"active":-23},"Kozhikode":{"hospital_obs":69,"home_obs":356,"total_obs":425,"hospital_today":82,"confirmed":158,"recovered":103,"deceased":0,"active":55},"Malappuram":{"hospital_obs":275,"home_obs":147,"total_obs":422,"hospital_today":84,"confirmed":242,"recovered":51,"deceased":0,"active":191},"Palakkad":{"hospital_obs":91,"home_obs":-43,"total_obs":48,"hospital_today":67,"confirmed":141,"recovered":40,"deceased":0,"active":101},"Pathanamthitta":{"hospital_obs":-39,"home_obs":112,"total_obs":73,"hospital_today":-24,"confirmed":20,"recovered":41,"deceased":0,"active":-21},"Thiruvananthapuram":{"hospital_obs":-120,"home_obs":705,"total_obs":585,"hospital_today":-5,"confirmed":297,"recovered":498,"deceased":3,"active":-206},"Thrissur":{"hospital_obs":-55,"home_obs":-1219,"total_obs":-1274,"hospital_today":-18,"confirmed":32,"recovered":65,"deceased":0,"active":-33},"Wayanad":{"hospital_obs":-12,"home_obs":38,"total_obs":26,"hospital_today":16,"confirmed":18,"recovered":48,"deceased":0,"active":-30}},"last_updated":"11-08-2020 7:46 PM"}