{"summary":{"Thiruvananthapuram":{"confirmed":152187,"recovered":123802,"active":27298,"deceased":999,"total_obs":74024,"hospital_obs":3572,"home_obs":70452,"hospital_today":522},"Kollam":{"confirmed":115991,"recovered":109799,"active":5776,"deceased":392,"total_obs":25978,"hospital_obs":1393,"home_obs":24585,"hospital_today":192},"Pathanamthitta":{"confirmed":78081,"recovered":65227,"active":12700,"deceased":146,"total_obs":11894,"hospital_obs":1482,"home_obs":10412,"hospital_today":196},"Alappuzha":{"confirmed":111154,"recovered":91990,"active":18676,"deceased":457,"total_obs":38681,"hospital_obs":1835,"home_obs":36846,"hospital_today":292},"Kottayam":{"confirmed":126798,"recovered":109725,"active":16790,"deceased":272,"total_obs":62023,"hospital_obs":2733,"home_obs":59290,"hospital_today":52},"Idukki":{"confirmed":46181,"recovered":31911,"active":14212,"deceased":52,"total_obs":16786,"hospital_obs":578,"home_obs":16208,"hospital_today":50},"Ernakulam":{"confirmed":203197,"recovered":148370,"active":54289,"deceased":499,"total_obs":104085,"hospital_obs":3463,"home_obs":100622,"hospital_today":258},"Thrissur":{"confirmed":155994,"recovered":118737,"active":36628,"deceased":611,"total_obs":79975,"hospital_obs":2536,"home_obs":77439,"hospital_today":385},"Palakkad":{"confirmed":91602,"recovered":67889,"active":23492,"deceased":209,"total_obs":50151,"hospital_obs":1624,"home_obs":48527,"hospital_today":301},"Malappuram":{"confirmed":174040,"recovered":136133,"active":37389,"deceased":495,"total_obs":56609,"hospital_obs":1603,"home_obs":55006,"hospital_today":356},"Kozhikode":{"confirmed":198917,"recovered":152084,"active":46170,"deceased":632,"total_obs":108404,"hospital_obs":2932,"home_obs":105472,"hospital_today":432},"Wayanad":{"confirmed":41842,"recovered":30898,"active":10834,"deceased":104,"total_obs":28336,"hospital_obs":732,"home_obs":27604,"hospital_today":155},"Kannur":{"confirmed":93578,"recovered":69900,"active":23227,"deceased":415,"total_obs":53033,"hospital_obs":1056,"home_obs":51977,"hospital_today":144},"Kasaragod":{"confirmed":49216,"recovered":37125,"active":11960,"deceased":122,"total_obs":14632,"hospital_obs":630,"home_obs":14002,"hospital_today":36}},"delta":{"Thiruvananthapuram":{"confirmed":3424,"recovered":1899,"active":1517,"deceased":8,"total_obs":3543,"hospital_obs":140,"home_obs":3403,"hospital_today":16},"Kollam":{"confirmed":1597,"recovered":1052,"active":543,"deceased":2,"total_obs":884,"hospital_obs":59,"home_obs":825,"hospital_today":7},"Pathanamthitta":{"confirmed":1082,"recovered":828,"active":254,"deceased":0,"total_obs":-214,"hospital_obs":-81,"home_obs":-133,"hospital_today":0},"Alappuzha":{"confirmed":2442,"recovered":970,"active":1472,"deceased":0,"total_obs":2729,"hospital_obs":7,"home_obs":2722,"hospital_today":94},"Kottayam":{"confirmed":2815,"recovered":1025,"active":1790,"deceased":0,"total_obs":1454,"hospital_obs":132,"home_obs":1322,"hospital_today":-1418},"Idukki":{"confirmed":1036,"recovered":228,"active":808,"deceased":0,"total_obs":839,"hospital_obs":33,"home_obs":806,"hospital_today":8},"Ernakulam":{"confirmed":3502,"recovered":2279,"active":1223,"deceased":0,"total_obs":1287,"hospital_obs":37,"home_obs":1250,"hospital_today":-299},"Thrissur":{"confirmed":3942,"recovered":1242,"active":2686,"deceased":14,"total_obs":5447,"hospital_obs":51,"home_obs":5396,"hospital_today":49},"Palakkad":{"confirmed":1936,"recovered":943,"active":993,"deceased":0,"total_obs":5886,"hospital_obs":46,"home_obs":5840,"hospital_today":102},"Malappuram":{"confirmed":3085,"recovered":1758,"active":1322,"deceased":4,"total_obs":4673,"hospital_obs":151,"home_obs":4522,"hospital_today":-22},"Kozhikode":{"confirmed":4238,"recovered":2660,"active":1561,"deceased":17,"total_obs":5405,"hospital_obs":143,"home_obs":5262,"hospital_today":103},"Wayanad":{"confirmed":769,"recovered":188,"active":581,"deceased":0,"total_obs":1077,"hospital_obs":50,"home_obs":1027,"hospital_today":70},"Kannur":{"confirmed":1525,"recovered":1143,"active":378,"deceased":4,"total_obs":1681,"hospital_obs":56,"home_obs":1625,"hospital_today":-16},"Kasaragod":{"confirmed":566,"recovered":81,"active":485,"deceased":0,"total_obs":2077,"hospital_obs":19,"home_obs":2058,"hospital_today":2}},"last_updated":"02-05-2021 7:16 PM"}