{"summary":{"cvc_public":332,"cvc_private":277,"cvc_total":312,"hcw_dose1":921,"hcw_dose2":555778,"flw_other_dose1":510331,"flw_other_dose2":224881,"flw_polling_dose1":571893,"flw_polling_dose2":536574,"age_appropriate_dose1":161375,"age_appropriate_dose2":338639,"tot_vaccinations":86347,"tot_person_vaccinations":6940821,"second_dose":6279083},"delta":{"cvc_public":318,"cvc_private":266,"cvc_total":127,"hcw_dose1":711,"hcw_dose2":6,"flw_other_dose1":45,"flw_other_dose2":2242,"flw_polling_dose1":5,"flw_polling_dose2":52,"age_appropriate_dose1":2363,"age_appropriate_dose2":83495,"tot_vaccinations":28123,"tot_person_vaccinations":506,"second_dose":3568},"last_updated":"20-05-2022 5:19 PM"}